[{"author":"Fabito","caption":"...","date":"2024-07-10T12:43:42.336Z","id":"pl5k9ddmc68","image":"https://media.tenor.com/0VuncPcO_yIAAAAM/hide-the-simpsons.gif","likes":["Fabito","Valito"]},{"author":"Valito","caption":"New Caption para mi post","date":"2024-07-10T12:47:25.218Z","id":"mi8drcuyseo","image":"https://media.tenor.com/lhUSFl0CnpEAAAAM/frenchie-french.gif","likes":["Fabito"]},{"author":"Valito","caption":"ÑamÑam","date":"2024-07-11T09:41:57.634Z","id":"gud3txmwlqo","image":"https://media.tenor.com/u3QduFHVtJ8AAAAM/tacos-dog.gif","likes":[]},{"id":"1nb7fuwfktmo","image":"https://media.tenor.com/BOaHBWIl25UAAAAM/espa%C3%B1a-bandera.gif","caption":"X ESPAÑA PAPI","author":"Fabito","date":"2024-07-23T12:44:52.427Z","likes":[]},{"id":"fbm1my9ygbc","image":"https://media.tenor.com/BOaHBWIl25UAAAAM/espa%C3%B1a-bandera.gif","caption":"X ESPAÑA PAPI","author":"Fabito","date":"2024-07-23T12:45:48.537Z","likes":[]}]